masking/__init__.py
masking/maskstring.py
masking-0.0.3.dist-info/LICENSE
masking-0.0.3.dist-info/METADATA
masking-0.0.3.dist-info/WHEEL
masking-0.0.3.dist-info/top_level.txt
masking-0.0.3.dist-info/RECORD
