Metadata-Version: 2.1
Name: masking
Version: 0.0.3
Summary: This package contains a function 'maskstring' to mask a given input string based on the index positions passed as arguments.
Home-page: https://github.com/sangram11/MASKING
Author: Sangram Mohanty
Author-email: odisha532@hotmail.com
License: UNKNOWN
Project-URL: BUG Tracker, https://github.com/sangram11/MASKING
Platform: UNKNOWN
Classifier: Programming Language :: Python :: 3
Classifier: License :: OSI Approved :: MIT License
Classifier: Operating System :: OS Independent
Requires-Python: >=3.6
